CloudVolume/BeamImager.py
CloudVolume/CloudVolume.py
CloudVolume/__init__.py
CloudVolume_multibeam-1.0.1.dist-info/METADATA
CloudVolume_multibeam-1.0.1.dist-info/WHEEL
CloudVolume_multibeam-1.0.1.dist-info/entry_points.txt
CloudVolume_multibeam-1.0.1.dist-info/top_level.txt
CloudVolume_multibeam-1.0.1.dist-info/RECORD
