Metadata-Version: 2.1
Name: CloudVolume_multibeam
Version: 1.0.1
Summary: Visualization and calculation volume of under water installation using processed multibeam data
Author: Samira Lashkari
Author-email: samira.lashkari@gmail.com
Classifier: Programming Language :: Python :: 3
Classifier: License :: OSI Approved :: MIT License
Classifier: Operating System :: OS Independent
Requires-Python: ==3.9.20
Requires-Dist: open3d==0.17.0
Requires-Dist: hdbscan==0.8.33
Requires-Dist: pandas==1.5.3
Requires-Dist: numpy==1.24.3
Requires-Dist: scikit-learn==1.3.0
Requires-Dist: matplotlib==3.7.2
